kzconfig/__init__.py
kzconfig/context.py
kzconfig/couch.py
kzconfig/dns.py
kzconfig/kazoo.py
kzconfig/kube.py
kzconfig/kubectl.py
kzconfig/meta.py
kzconfig/sup.py
kzconfig/util.py
kzconfig/cli/__init__.py
kzconfig/cli/kubectl.py
kzconfig/cli/sup.py
kzconfig-0.3.3.dist-info/DESCRIPTION.rst
kzconfig-0.3.3.dist-info/METADATA
kzconfig-0.3.3.dist-info/RECORD
kzconfig-0.3.3.dist-info/WHEEL
kzconfig-0.3.3.dist-info/entry_points.txt
kzconfig-0.3.3.dist-info/metadata.json
kzconfig-0.3.3.dist-info/top_level.txt
tasks/__init__.py
tasks/py.py
tasks/test.py
