Metadata-Version: 2.0
Name: kzconfig
Version: 0.3.3
Summary: Convenience library for configuring Kazoo & it's components
Home-page: https://github.com/telephoneorg/kzconfig
Author: Joe Black
Author-email: me@joeblack.nyc
License: Apache 2.0
Download-URL: https://github.com/telephoneorg/kzconfig/tarball/v0.3.3
Platform: UNKNOWN
Classifier: Development Status :: 3 - Alpha
Classifier: Intended Audience :: Developers
Classifier: Intended Audience :: System Administrators
Classifier: Operating System :: OS Independent
Classifier: Natural Language :: English
Classifier: License :: OSI Approved :: Apache Software License
Classifier: Programming Language :: Python :: 3.6
Classifier: Programming Language :: Python :: 3 :: Only
Classifier: Topic :: Internet :: WWW/HTTP
Classifier: Topic :: Software Development
Classifier: Topic :: System
Classifier: Topic :: System :: Systems Administration
Requires-Dist: click
Requires-Dist: couchdb
Requires-Dist: dnsimple
Requires-Dist: dnspython
Requires-Dist: kazoo-sdk (>=0.2.3)
Requires-Dist: pyrkube (>=0.2.5)
Requires-Dist: requests
